litestar_ormar/__init__.py
litestar_ormar/helpers.py
litestar_ormar/lifespan.py
litestar_ormar/repositories.py
litestar_ormar-0.0.6.dist-info/AUTHORS.rst
litestar_ormar-0.0.6.dist-info/LICENSE
litestar_ormar-0.0.6.dist-info/METADATA
litestar_ormar-0.0.6.dist-info/WHEEL
litestar_ormar-0.0.6.dist-info/RECORD
