Metadata-Version: 2.3
Name: litestar-ormar
Version: 0.0.6
Summary: Ormar integration for Litestar.
License: Apache-2.0
Author: Dominik Kozaczko
Author-email: dominik@kozaczko.info
Requires-Python: >=3.11,<4.0
Classifier: Development Status :: 2 - Pre-Alpha
Classifier: License :: OSI Approved :: Apache Software License
Classifier: Programming Language :: Python :: 3
Classifier: Programming Language :: Python :: 3.11
Classifier: Programming Language :: Python :: 3.12
Classifier: Programming Language :: Python :: 3.13
Classifier: Topic :: Software Development :: Libraries
Requires-Dist: litestar (>=2.15.1,<3.0.0)
Requires-Dist: ormar (>=0.20.2,<0.21.0)
